linkedin_scrapper/__init__.py
linkedin_scrapper/account.py
linkedin_scrapper/functions.py
linkedin_scrapper/person.py
linkedin_scrapper-1.1.dist-info/DESCRIPTION.rst
linkedin_scrapper-1.1.dist-info/METADATA
linkedin_scrapper-1.1.dist-info/RECORD
linkedin_scrapper-1.1.dist-info/WHEEL
linkedin_scrapper-1.1.dist-info/metadata.json
linkedin_scrapper-1.1.dist-info/top_level.txt
