Metadata-Version: 1.1
Name: linkedin-scrapper
Version: 1.1
Summary: A way to scrape user datas from linkedin
Home-page: https://github.com/BenyDZ/Linkedin-Scrapper
Author: Beny Dziengue
Author-email: bdziengue@gmail.com
License: UNKNOWN
Keywords: linkedin,scraping,scraper
Platform: UNKNOWN
Classifier: Programming Language :: Python :: 3
Classifier: License :: OSI Approved :: MIT License
Classifier: Operating System :: OS Independent
